gaggiuino_api/__init__.py
gaggiuino_api/api.py
gaggiuino_api/const.py
gaggiuino_api/exceptions.py
gaggiuino_api/models.py
gaggiuino_api/py.typed
gaggiuino_api/tools.py
gaggiuino_api-0.1.12.dist-info/METADATA
gaggiuino_api-0.1.12.dist-info/WHEEL
gaggiuino_api-0.1.12.dist-info/RECORD
