Metadata-Version: 2.4
Name: gaggiuino_api
Version: 0.1.12
Summary: Gaggiuino REST Api Wrapper
Author-email: Alexey ALERT Rubashёff <alexey.rubasheff@gmail.com>
Requires-Python: >=3.13
Requires-Dist: aiohttp
